README.md
pyproject.toml
setup.cfg
setup.py
do_sdk_platform/__init__.py
do_sdk_platform/api_client.py
do_sdk_platform/api_response.py
do_sdk_platform/configuration.py
do_sdk_platform/exceptions.py
do_sdk_platform/py.typed
do_sdk_platform/rest.py
do_sdk_platform.egg-info/PKG-INFO
do_sdk_platform.egg-info/SOURCES.txt
do_sdk_platform.egg-info/dependency_links.txt
do_sdk_platform.egg-info/requires.txt
do_sdk_platform.egg-info/top_level.txt
do_sdk_platform/api/__init__.py
do_sdk_platform/api/authentication_api.py
do_sdk_platform/api/billing_api.py
do_sdk_platform/api/data_platform_api.py
do_sdk_platform/api/entities_api.py
do_sdk_platform/api/file_api.py
do_sdk_platform/api/tools_api.py
do_sdk_platform/models/__init__.py
do_sdk_platform/models/add_column.py
do_sdk_platform/models/add_column_boolean.py
do_sdk_platform/models/add_column_date.py
do_sdk_platform/models/add_column_editor.py
do_sdk_platform/models/add_column_expression.py
do_sdk_platform/models/add_column_file.py
do_sdk_platform/models/add_column_float.py
do_sdk_platform/models/add_column_integer.py
do_sdk_platform/models/add_column_lookup.py
do_sdk_platform/models/add_column_reference.py
do_sdk_platform/models/add_column_select.py
do_sdk_platform/models/add_column_text.py
do_sdk_platform/models/add_column_url.py
do_sdk_platform/models/add_column_user.py
do_sdk_platform/models/add_credits_request_schema_dto.py
do_sdk_platform/models/admin_organization_schema_dto.py
do_sdk_platform/models/billing_address_schema_dto.py
do_sdk_platform/models/billing_check200_response.py
do_sdk_platform/models/capture_event_schema_dto.py
do_sdk_platform/models/capture_event_schema_dto_event_name.py
do_sdk_platform/models/chat_thread.py
do_sdk_platform/models/cluster_schema_dto.py
do_sdk_platform/models/code_exeuction.py
do_sdk_platform/models/column.py
do_sdk_platform/models/column_boolean_base.py
do_sdk_platform/models/column_date_base.py
do_sdk_platform/models/column_editor_base.py
do_sdk_platform/models/column_expression_base.py
do_sdk_platform/models/column_file_base.py
do_sdk_platform/models/column_file_base_config_file.py
do_sdk_platform/models/column_float_base.py
